{
    "32": {
        "u": 32,
        "nickname": "Eledao",
        "tier": 1,
        "arg": "Ok, she is a manipulative woman throughout the series, able to continuously get away with conning people and organizing the ranking battles. Also In NMH 3, she inexplicably can fly through space, as well as being able to fire laser beams from her eyes.\n"
    },
    "51": {
        "u": 51,
        "nickname": "Digital_Devil",
        "tags": [
            "bj",
            "dm"
        ]
    },
    "86": {
        "u": 86,
        "nickname": "Demontty",
        "tags": [
            "st",
            "mm"
        ]
    },
    "88": {
        "u": 88,
        "nickname": "Demontty",
        "tags": [
            "cl",
            "di",
            "tm",
            "hp",
            "tc"
        ]
    },
    "324": {
        "u": 324,
        "nickname": "Cyrus",
        "tags": [
            "dr",
            "sr"
        ]
    },
    "327": {
        "u": 327,
        "nickname": "Cyrus",
        "tags": [
            "dr"
        ]
    },
    "345": {
        "u": 345,
        "nickname": "FavChanger",
        "tags": [
            "hz",
            "cl",
            "di",
            "fm",
            "tm",
            "fn",
            "tn",
            "hp",
            "th",
            "pr",
            "rw"
        ],
        "name": "Simon the Digger"
    },
    "478": {
        "u": 478,
        "nickname": "Cyrus",
        "tags": [
            "id",
            "mr",
            "ir"
        ]
    },
    "491": {
        "u": 491,
        "nickname": "Cyrus",
        "tags": [
            "sr",
            "rl"
        ],
        "sub": "None"
    },
    "495": {
        "u": 495,
        "nickname": "Cyrus",
        "tags": [
            "gi"
        ],
        "sub": "None"
    },
    "502": {
        "u": 502,
        "nickname": "Cyrus",
        "tags": [
            "sc",
            "cf",
            "rl",
            "cm",
            "ke"
        ]
    },
    "504": {
        "u": 504,
        "nickname": "Cyrus",
        "tags": [
            "cl",
            "sc",
            "en",
            "cb",
            "rl",
            "cm"
        ]
    },
    "505": {
        "u": 505,
        "nickname": "Cyrus",
        "tags": [
            "hr",
            "mt",
            "cl",
            "sc",
            "mo",
            "sl",
            "cm",
            "Fish-Men"
        ]
    },
    "506": {
        "u": 506,
        "nickname": "Cyrus",
        "tags": [
            "cl",
            "ml",
            "sc",
            "cm"
        ]
    },
    "507": {
        "u": 507,
        "nickname": "Cyrus",
        "tags": [
            "st",
            "hr",
            "hz",
            "cl",
            "sc",
            "dm",
            "dh",
            "sr",
            "rl",
            "cm"
        ],
        "sub": "None"
    },
    "508": {
        "u": 508,
        "nickname": "Cyrus",
        "sub": "None"
    },
    "509": {
        "u": 509,
        "nickname": "Cyrus",
        "tags": [
            "ml",
            "sa",
            "cm",
            "sh",
            "te"
        ]
    },
    "510": {
        "u": 510,
        "nickname": "Cyrus",
        "tags": [
            "sc",
            "dh",
            "sr",
            "ar",
            "vn",
            "cm",
            "sh"
        ]
    },
    "511": {
        "u": 511,
        "nickname": "Cyrus",
        "tags": [
            "cl",
            "sc",
            "cm"
        ],
        "sub": "None"
    },
    "512": {
        "u": 512,
        "nickname": "Cyrus",
        "tags": [
            "hz",
            "cl",
            "ml",
            "sc",
            "sr",
            "cm"
        ],
        "sub": "None"
    },
    "513": {
        "u": 513,
        "nickname": "SunshineDreamer",
        "tags": [
            "cl",
            "ps",
            "sc",
            "ip",
            "rl",
            "sa",
            "cm",
            "te"
        ],
        "name": "Trafalgar Law",
        "tier": 6,
        "arg": "Should be a 7, strong enough, checked in official WC discord"
    },
    "514": {
        "u": 514,
        "nickname": "Cyrus",
        "tags": [
            "cl",
            "sc",
            "cm",
            "sh"
        ],
        "sub": "None"
    },
    "515": {
        "u": 515,
        "nickname": "Cyrus",
        "tags": [
            "sl",
            "cl",
            "di",
            "cm"
        ]
    },
    "516": {
        "u": 516,
        "nickname": "Cyrus",
        "tags": [
            "hr",
            "hz",
            "cl",
            "sc",
            "sr",
            "ev",
            "rl",
            "vn",
            "cm"
        ],
        "sub": "None",
        "name": "Akainu"
    },
    "517": {
        "u": 517,
        "nickname": "Cyrus",
        "tags": [
            "hr",
            "hz",
            "cl",
            "sc",
            "sr",
            "rl",
            "cm",
            "sh"
        ],
        "sub": "None",
        "name": "Aokiji"
    },
    "518": {
        "u": 518,
        "nickname": "Cyrus",
        "tags": [
            "st",
            "hr",
            "hz",
            "cl",
            "sc",
            "hl",
            "pi",
            "cb",
            "rl",
            "sa",
            "cm",
            "sh",
            "ke"
        ],
        "sub": "None",
        "tier": 7,
        "arg": "If the Yonkous are ranted Tier 7, then he should be Tier 6."
    },
    "519": {
        "u": 519,
        "nickname": "Cyrus",
        "tags": [
            "bj",
            "sc",
            "bk",
            "sa",
            "vn",
            "cm",
            "sh"
        ],
        "sub": "None"
    },
    "520": {
        "u": 520,
        "nickname": "Cyrus",
        "tags": [
            "sc",
            "tc",
            "cm"
        ],
        "sub": "None"
    },
    "521": {
        "u": 521,
        "nickname": "Cyrus",
        "tags": [
            "hr",
            "hz",
            "cl",
            "sc",
            "di",
            "sr",
            "rl",
            "cm"
        ],
        "sub": "None",
        "name": "Kizaru"
    },
    "522": {
        "u": 522,
        "nickname": "Cyrus",
        "tags": [
            "th",
            "rl"
        ],
        "sub": "None"
    },
    "523": {
        "u": 523,
        "nickname": "Cyrus",
        "tags": [
            "hr",
            "hz",
            "cl",
            "sc",
            "sr",
            "sa",
            "cm",
            "sh"
        ],
        "sub": "None"
    },
    "525": {
        "u": 525,
        "nickname": "Cyrus",
        "tags": [
            "cm"
        ],
        "sub": "None",
        "name": "Edward Newgate"
    },
    "526": {
        "u": 526,
        "nickname": "Everythingman101",
        "tags": [
            "hr",
            "hz",
            "sc",
            "di",
            "vn"
        ],
        "sub": "None"
    },
    "527": {
        "u": 527,
        "nickname": "Cyrus",
        "tags": [
            "hr",
            "hz",
            "sc",
            "sr",
            "vn",
            "cm",
            "sh",
            "pm"
        ],
        "sub": "None",
        "name": "Marshall D. Teach"
    },
    "542": {
        "u": 542,
        "nickname": "Cyrus",
        "tags": [
            "hr",
            "hz",
            "cl",
            "sc",
            "di",
            "sr",
            "ev",
            "sa",
            "fa"
        ]
    },
    "1791": {
        "u": 1791,
        "nickname": "SunshineDreamer",
        "image": "[n]HhwGxpO.jpg",
        "source": "https://media.discordapp.net/attachments/767806491302166559/1015686663537705051/unknown.png"
    },
    "1793": {
        "u": 1793,
        "nickname": "SunshineDreamer",
        "image": "[n]jQmslMF.jpg",
        "source": "https://cdn.discordapp.com/attachments/767806491302166559/1015687405644283924/unknown.png"
    },
    "2120": {
        "u": 2120,
        "nickname": "Jollymerr",
        "tags": [
            "cl",
            "fn",
            "gn",
            "sa",
            "cm"
        ],
        "tier": 5,
        "arg": "is canonically stated to be on equal footing with Achilles (teir 7)"
    },
    "2579": {
        "u": 2579,
        "nickname": "Paragon_4376",
        "tags": [
            "tc",
            "cm",
            "sh"
        ],
        "image": "[n]SR-npc-Nazir.jpg",
        "source": "https://images.uesp.net/0/02/SR-npc-Nazir.jpg"
    },
    "2600": {
        "u": 2600,
        "nickname": "Paragon_4376",
        "tags": [
            "nj",
            "cm",
            "sh"
        ],
        "image": ""
    },
    "2629": {
        "u": 2629,
        "nickname": "Paragon_4376",
        "tags": [
            "me",
            "tc",
            "cc",
            "cm",
            "sh",
            "nc"
        ],
        "image": ""
    },
    "2809": {
        "u": 2809,
        "nickname": "KaizerRyu",
        "tags": [
            "mt",
            "fm",
            "mo"
        ]
    },
    "2810": {
        "u": 2810,
        "nickname": "KaizerRyu",
        "tags": [
            "mt",
            "fm",
            "mo",
            "bk",
            "cm",
            "fa"
        ]
    },
    "3041": {
        "u": 3041,
        "nickname": "LoLRaven",
        "tags": [
            "ur",
            "dn",
            "ai",
            "sr",
            "fa"
        ]
    },
    "3085": {
        "u": 3085,
        "nickname": "Chibikingsai",
        "tags": [
            "cl",
            "dg",
            "ai",
            "cm"
        ],
        "image": "",
        "source": "https://wikimon.net/Kaiser_Greymon"
    },
    "3377": {
        "u": 3377,
        "nickname": "Dreadrotz",
        "tags": [
            "dh"
        ]
    },
    "3610": {
        "u": 3610,
        "nickname": "Anongus",
        "world": "Nickelodeon"
    },
    "3612": {
        "u": 3612,
        "nickname": "Digital_Devil",
        "nsfw": "https://cdn.donmai.us/sample/c5/46/__hatsune_miku_and_jenny_wakeman_vocaloid_and_1_more_drawn_by_aetherion__sample-c5466f9c177c005a92ea504efaa73e02.jpg"
    },
    "3762": {
        "u": 3762,
        "nickname": "Paragon_4376",
        "tags": [
            "hz",
            "dn",
            "cm",
            "ha",
            "sh"
        ]
    },
    "3763": {
        "u": 3763,
        "nickname": "Paragon_4376",
        "tags": [
            "hz",
            "cm",
            "sh"
        ]
    },
    "3764": {
        "u": 3764,
        "nickname": "Paragon_4376",
        "tags": [
            "hr",
            "cm",
            "ha",
            "sh"
        ]
    },
    "3932": {
        "u": 3932,
        "nickname": "Paragon_4376",
        "tags": [
            "hz",
            "sc",
            "sl",
            "th",
            "cm",
            "sh"
        ]
    },
    "4574": {
        "u": 4574,
        "nickname": "Sogen",
        "tags": [
            "un"
        ]
    },
    "4576": {
        "u": 4576,
        "nickname": "Sogen",
        "tags": [
            "un"
        ]
    },
    "4655": {
        "u": 4655,
        "nickname": "Digital_Devil",
        "tags": [
            "di"
        ]
    },
    "4658": {
        "u": 4658,
        "nickname": "Digital_Devil",
        "tags": [
            "di"
        ]
    },
    "4702": {
        "u": 4702,
        "nickname": "Digital_Devil",
        "tags": [
            "sc"
        ]
    },
    "4892": {
        "u": 4892,
        "nickname": "Sogen",
        "tags": [
            "ml",
            "ps",
            "sc",
            "cm",
            "nc"
        ]
    },
    "4894": {
        "u": 4894,
        "nickname": "Uneasycloud",
        "tags": [
            "ps",
            "cm"
        ]
    },
    "4897": {
        "u": 4897,
        "nickname": "Sogen",
        "tags": [
            "cl"
        ]
    },
    "5020": {
        "u": 5020,
        "nickname": "Sogen",
        "tags": [
            "th"
        ]
    },
    "5026": {
        "u": 5026,
        "nickname": "Sogen",
        "tags": [
            "st",
            "sc",
            "sh"
        ]
    },
    "5027": {
        "u": 5027,
        "nickname": "Sogen",
        "tags": [
            "st",
            "sc",
            "nj",
            "sr",
            "cm",
            "sh"
        ]
    },
    "5069": {
        "u": 5069,
        "nickname": "Sogen",
        "tags": [
            "un"
        ]
    },
    "5073": {
        "u": 5073,
        "nickname": "Sogen",
        "tags": [
            "un"
        ]
    },
    "5074": {
        "u": 5074,
        "nickname": "Sogen",
        "tags": [
            "un"
        ]
    },
    "5102": {
        "u": 5102,
        "nickname": "Broken Genesis",
        "tags": [
            "ye"
        ]
    },
    "5118": {
        "u": 5118,
        "nickname": "LoLRaven",
        "tags": [
            "sr"
        ]
    },
    "5119": {
        "u": 5119,
        "nickname": "LoLRaven",
        "tags": [
            "sr",
            "pr",
            "im"
        ]
    },
    "5160": {
        "u": 5160,
        "nickname": "LoLRaven",
        "tags": [
            "sd",
            "sa",
            "vn",
            "cm",
            "sh"
        ]
    },
    "5232": {
        "u": 5232,
        "nickname": "SunshineDreamer",
        "sub": "None",
        "world": "Agents of SHIELD"
    },
    "5406": {
        "u": 5406,
        "nickname": "SunshineDreamer",
        "world": "Castlevania "
    },
    "5409": {
        "u": 5409,
        "nickname": "Sogen",
        "tags": [
            "vn",
            "un"
        ]
    },
    "5410": {
        "u": 5410,
        "nickname": "Sogen",
        "tags": [
            "un"
        ]
    },
    "5411": {
        "u": 5411,
        "nickname": "Sogen",
        "tags": [
            "un"
        ]
    },
    "5412": {
        "u": 5412,
        "nickname": "Sogen",
        "tags": [
            "un"
        ]
    },
    "5413": {
        "u": 5413,
        "nickname": "Sogen",
        "tags": [
            "un"
        ]
    },
    "5466": {
        "u": 5466,
        "nickname": "Eledao",
        "image": "iya__sample_9bc875f2c546bd37feccb727a2363398.jpg",
        "source": "https://danbooru.donmai.us/posts/1525222"
    },
    "5557": {
        "u": 5557,
        "nickname": "washuu",
        "tags": [
            "hz",
            "cl",
            "ps",
            "sc",
            "di",
            "tm",
            "im"
        ]
    },
    "5737": {
        "u": 5737,
        "nickname": "Sogen",
        "tags": [
            "st"
        ]
    },
    "5740": {
        "u": 5740,
        "nickname": "Cyrus",
        "tags": [
            "cl",
            "sc",
            "sl",
            "md",
            "sr",
            "cm",
            "sh"
        ],
        "name": "Helun"
    },
    "5780": {
        "u": 5780,
        "nickname": "Uneasycloud",
        "image": "sample_2c0a044d4dbbce5d35a499813012e20c.jpg",
        "source": "https://chan.sankakucomplex.com/post/show/6068363"
    },
    "5785": {
        "u": 5785,
        "nickname": "Sogen",
        "tags": [
            "hl"
        ]
    },
    "5788": {
        "u": 5788,
        "nickname": "Sogen",
        "tags": [
            "st"
        ]
    },
    "5904": {
        "u": 5904,
        "nickname": "FinSexual92",
        "tags": [
            "me",
            "cm"
        ]
    },
    "5954": {
        "u": 5954,
        "nickname": "Cyrus",
        "tags": [
            "st",
            "ml",
            "bj",
            "cm",
            "gi",
            "Masochist"
        ],
        "image": "14b55884544e063c3c566240e6e34054.jpg",
        "source": "https://chan.sankakucomplex.com/post/show/18320092",
        "name": "Darkness"
    },
    "6063": {
        "u": 6063,
        "nickname": "Dreadrotz",
        "tags": [
            "me",
            "cm"
        ]
    },
    "6077": {
        "u": 6077,
        "nickname": "TheFlatCat",
        "image": "ln_08_12.jpg",
        "source": "https://vignette.wikia.nocookie.net/tensei-shitara-slime-datta-ken/images/c/c2/LN_08_12.jpg"
    },
    "6080": {
        "u": 6080,
        "nickname": "Sogen",
        "tags": [
            "pl",
            "sc",
            "cm"
        ]
    },
    "6101": {
        "u": 6101,
        "nickname": "Sogen",
        "tags": [
            "st",
            "cm",
            "rw"
        ]
    },
    "6196": {
        "u": 6196,
        "nickname": "Uneasycloud",
        "nsfw": "https://cdn.donmai.us/sample/9b/2e/__misaka_mikoto_toaru_majutsu_no_index_and_1_more_drawn_by_ao_banana__sample-9b2e1a943c23b006d02b730dbc652969.jpg"
    },
    "6428": {
        "u": 6428,
        "nickname": "Sogen",
        "tags": [
            "un"
        ]
    },
    "6429": {
        "u": 6429,
        "nickname": "Sogen",
        "tags": [
            "un"
        ]
    },
    "6717": {
        "u": 6717,
        "nickname": "Cyrus",
        "tags": [
            "th"
        ],
        "sub": "None"
    },
    "6720": {
        "u": 6720,
        "nickname": "Cyrus",
        "tags": [
            "dr"
        ]
    },
    "6721": {
        "u": 6721,
        "nickname": "Cyrus",
        "tags": [
            "cf",
            "cl",
            "ml",
            "sc",
            "pc",
            "sr",
            "sh",
            "te"
        ]
    },
    "6722": {
        "u": 6722,
        "nickname": "Cyrus",
        "tags": [
            "cl",
            "sc",
            "sa",
            "cm",
            "sh",
            "gi"
        ],
        "sub": "None"
    },
    "6756": {
        "u": 6756,
        "nickname": "Sogen",
        "tags": [
            "ps"
        ]
    },
    "7580": {
        "u": 7580,
        "nickname": "Eledao",
        "tags": [
            "st",
            "cl",
            "ps",
            "bj",
            "dr",
            "pl",
            "sc",
            "tm",
            "py",
            "mu",
            "sr",
            "rg",
            "pr",
            "cm"
        ],
        "sub": "Parasite Eve"
    },
    "7581": {
        "u": 7581,
        "nickname": "Eledao",
        "tags": [
            "mt",
            "bj",
            "pl",
            "mo",
            "bk",
            "th",
            "sr"
        ],
        "name": "Eve"
    },
    "8031": {
        "u": 8031,
        "nickname": "FinSexual92",
        "tags": [
            "cl",
            "sc",
            "di",
            "py",
            "sl",
            "hl",
            "rs",
            "sd",
            "me",
            "cf",
            "ar"
        ]
    },
    "8170": {
        "u": 8170,
        "nickname": "Digital_Devil",
        "tags": [
            "en"
        ]
    },
    "8209": {
        "u": 8209,
        "nickname": "Eledao",
        "image": "",
        "source": "https://64.media.tumblr.com/4ff343d97883c453ef0af2edc943624e/tumblr_on7gs4ToVv1vd8fpoo3_500.jpg"
    },
    "8470": {
        "u": 8470,
        "nickname": "Eledao",
        "image": ""
    },
    "8479": {
        "u": 8479,
        "nickname": "SetDarsia",
        "image": "[n]WaqZlIT.jpg",
        "source": "https://64.media.tumblr.com/4a58f87db78ea82f0a327f67e77fa137/tumblr_o7wps8fifK1qk38qio2_1280.png"
    },
    "8674": {
        "u": 8674,
        "nickname": "Eledao",
        "image": ""
    },
    "8697": {
        "u": 8697,
        "nickname": "Sogen",
        "tags": [
            "ps",
            "dr",
            "ur"
        ]
    },
    "8714": {
        "u": 8714,
        "nickname": "LoLRaven",
        "tags": [
            "sh"
        ]
    },
    "8745": {
        "u": 8745,
        "nickname": "FinSexual92",
        "tags": [
            "dm"
        ]
    },
    "8751": {
        "u": 8751,
        "nickname": "Sogen",
        "tags": [
            "ps"
        ]
    },
    "8752": {
        "u": 8752,
        "nickname": "Sogen",
        "tags": [
            "st",
            "sc",
            "cm",
            "sh"
        ]
    },
    "8769": {
        "u": 8769,
        "nickname": "Rhivan",
        "tags": [
            "st",
            "cl",
            "ps",
            "cr",
            "ip",
            "pt",
            "rl",
            "cm"
        ]
    },
    "8771": {
        "u": 8771,
        "nickname": "Sogen",
        "tags": [
            "cl",
            "sc",
            "di",
            "sl",
            "dn"
        ]
    },
    "8849": {
        "u": 8849,
        "nickname": "Aridwolverine",
        "image": "d8yzaiz_80ec11b5_f0a4_40f0_af63_7f9ef65cc39a.jpg",
        "source": "https://www.deviantart.com/jasonchanart/art/Chandra-542482955"
    },
    "8850": {
        "u": 8850,
        "nickname": "Zelred",
        "image": "https://i.imgur.com/Yy1TZDql.png",
        "source": "https://imgur.com/Yy1TZDq",
        "tags": [
            "nc"
        ]
    },
    "8859": {
        "u": 8859,
        "nickname": "SetDarsia",
        "tags": [
            "st",
            "ps",
            "py",
            "ip",
            "gd",
            "el",
            "im"
        ],
        "image": ""
    },
    "8873": {
        "u": 8873,
        "nickname": "Sogen",
        "tags": [
            "un"
        ]
    },
    "8874": {
        "u": 8874,
        "nickname": "Sogen",
        "tags": [
            "un"
        ]
    },
    "8878": {
        "u": 8878,
        "nickname": "Sogen",
        "tags": [
            "al"
        ]
    },
    "8893": {
        "u": 8893,
        "nickname": "Sogen",
        "tags": [
            "vp"
        ]
    },
    "9031": {
        "u": 9031,
        "nickname": "Sogen",
        "tags": [
            "ur"
        ]
    },
    "9035": {
        "u": 9035,
        "nickname": "Sogen",
        "tags": [
            "ur"
        ]
    },
    "9041": {
        "u": 9041,
        "nickname": "FinSexual92",
        "tags": [
            "sc",
            "hl",
            "me",
            "pc",
            "rl",
            "cm",
            "sh"
        ]
    },
    "9138": {
        "u": 9138,
        "nickname": "Eledao",
        "tags": [
            "cl",
            "ev"
        ]
    },
    "9239": {
        "u": 9239,
        "nickname": "Cyrus",
        "tags": [
            "sc",
            "me",
            "sr",
            "cm",
            "ir"
        ],
        "image": "sample_44665774024dd264ae51653971a5f9c7.jpg",
        "source": "https://chan.sankakucomplex.com/post/show/6605320",
        "nsfw": "https://cdn.donmai.us/sample/20/36/__ahri_league_of_legends_drawn_by_ricegnat__sample-203651c9cc9a8862424de6d029d8323f.jpg"
    },
    "9561": {
        "u": 9561,
        "nickname": "SunshineDreamer",
        "image": "sample_8327449dbdd49f8e768e8ad97b71e57d.jpg",
        "source": "https://chan.sankakucomplex.com/post/show/7447190"
    },
    "9564": {
        "u": 9564,
        "nickname": "SunshineDreamer",
        "image": "fd6885a16737630ff3d4013deb267d68.jpg",
        "source": "https://chan.sankakucomplex.com/post/show/5166555"
    },
    "9565": {
        "u": 9565,
        "nickname": "SunshineDreamer",
        "image": "upa__sample_86559c6ef601ea923e66846c83e2e2fb.jpg",
        "source": "https://danbooru.donmai.us/posts/3582115"
    },
    "9571": {
        "u": 9571,
        "nickname": "SunshineDreamer",
        "image": "910__sample_dfbcf063e27fcd68b7d54f56ea2cec5e.jpg",
        "source": "https://danbooru.donmai.us/posts/2253568"
    },
    "9573": {
        "u": 9573,
        "nickname": "SunshineDreamer",
        "image": "upa__sample_6f7b3dd3c5370262ce16b273810b50b7.jpg",
        "source": "https://danbooru.donmai.us/posts/3710311"
    },
    "9577": {
        "u": 9577,
        "nickname": "SunshineDreamer",
        "image": "upa__sample_de2fdba0d23dd71a7f02188c2bd5bc84.jpg",
        "source": "https://danbooru.donmai.us/posts/2245001"
    },
    "9579": {
        "u": 9579,
        "nickname": "SunshineDreamer",
        "image": "sample_992d1a638829d1aa61d1d96e6eaa595d.jpg",
        "source": "https://chan.sankakucomplex.com/post/show/7188727"
    },
    "9585": {
        "u": 9585,
        "nickname": "LoLRaven",
        "tags": [
            "hz",
            "sd"
        ]
    },
    "9594": {
        "u": 9594,
        "nickname": "Lunasmeow",
        "tags": [
            "sl",
            "ar"
        ]
    },
    "9597": {
        "u": 9597,
        "nickname": "SunshineDreamer",
        "image": "sample_c7d82e61b0811d25e0a9205557275999.jpg",
        "source": "https://chan.sankakucomplex.com/post/show/6839511"
    },
    "9598": {
        "u": 9598,
        "nickname": "SunshineDreamer",
        "image": "sample_b2b0fabad03aae5f87c4e2fa9b11000b.jpg",
        "source": "https://chan.sankakucomplex.com/post/show/7516098"
    },
    "9734": {
        "u": 9734,
        "nickname": "SunshineDreamer",
        "image": "[n]__shub_niggurath_original_and_1_more_drawn_by_akefumi__sample-4c12229700bf24d87aef6c6802e9cdfa.jpg",
        "source": "https://cdn.donmai.us/sample/4c/12/__shub_niggurath_original_and_1_more_drawn_by_akefumi__sample-4c12229700bf24d87aef6c6802e9cdfa.jpg"
    },
    "9775": {
        "u": 9775,
        "nickname": "Dreadrotz",
        "image": "sample_e07cbaa9103f4e0b705e287ab573ebad.jpg",
        "source": "https://chan.sankakucomplex.com/post/show/17714017"
    },
    "9827": {
        "u": 9827,
        "nickname": "Dan-San",
        "image": "ie_gienara__1e9e5c6e20564046b427763efa88d318.png",
        "source": "https://danbooru.donmai.us/posts/3864698",
        "nsfw": "None"
    },
    "9833": {
        "u": 9833,
        "nickname": "Z",
        "tags": [
            "Genderbender"
        ]
    },
    "9838": {
        "u": 9838,
        "nickname": "Meep",
        "tags": [
            "M",
            "tw"
        ]
    },
    "9850": {
        "u": 9850,
        "nickname": "Dreadrotz",
        "image": "sample_c90cf5701bf079f96c617db8aa3da030.jpg",
        "source": "https://chan.sankakucomplex.com/post/show/6624760"
    },
    "9901": {
        "u": 9901,
        "nickname": "Cyrus",
        "tags": [
            "sc",
            "hr",
            "dr",
            "ir"
        ]
    },
    "9902": {
        "u": 9902,
        "nickname": "Cyrus",
        "tags": [
            "sc",
            "sh"
        ]
    },
    "10321": {
        "u": 10321,
        "nickname": "TheFlatCat",
        "tags": [
            "ml"
        ]
    },
    "10400": {
        "u": 10400,
        "nickname": "Eledao",
        "nsfw": "https://cdnb.artstation.com/p/assets/images/images/041/213/513/large/p-o-p-a-3d-animations-amanda-sparkle-zoey-big-ass-2021-wallpaper.jpg"
    },
    "10522": {
        "u": 10522,
        "nickname": "LoLRaven",
        "tags": [
            "ps",
            "ip",
            "hl",
            "sd",
            "gn",
            "fa"
        ]
    },
    "10621": {
        "u": 10621,
        "nickname": "LoLRaven",
        "tags": [
            "pr"
        ]
    },
    "10622": {
        "u": 10622,
        "nickname": "LoLRaven",
        "tags": [
            "sl"
        ]
    },
    "10623": {
        "u": 10623,
        "nickname": "LoLRaven",
        "tags": [
            "mo",
            "hl"
        ]
    },
    "10624": {
        "u": 10624,
        "nickname": "LoLRaven",
        "tags": [
            "sn",
            "ha"
        ]
    },
    "10635": {
        "u": 10635,
        "nickname": "LoLRaven",
        "tags": [
            "sd",
            "wh",
            "sr"
        ]
    },
    "10806": {
        "u": 10806,
        "nickname": "FinSexual92",
        "tags": [
            "sd",
            "sr",
            "rg",
            "cm",
            "Werewolf"
        ]
    },
    "10988": {
        "u": 10988,
        "nickname": "Eledao",
        "tags": [
            "bj"
        ]
    },
    "11324": {
        "u": 11324,
        "nickname": "Sogen",
        "tags": [
            "ps",
            "pl"
        ]
    },
    "11422": {
        "u": 11422,
        "nickname": "Sogen",
        "tags": [
            "M"
        ]
    },
    "11426": {
        "u": 11426,
        "nickname": "Sogen",
        "tags": [
            "M"
        ]
    },
    "11441": {
        "u": 11441,
        "nickname": "Sogen",
        "tags": [
            "dr",
            "id",
            "pl",
            "ur",
            "cr",
            "sc",
            "im"
        ]
    },
    "11442": {
        "u": 11442,
        "nickname": "Sogen",
        "tags": [
            "M",
            "O",
            "ps",
            "dr",
            "id",
            "ur",
            "cr",
            "sc",
            "ip",
            "dm",
            "cm",
            "im"
        ]
    },
    "11580": {
        "u": 11580,
        "nickname": "Sogen",
        "tags": [
            "ps"
        ]
    },
    "11684": {
        "u": 11684,
        "nickname": "Sogen",
        "tags": [
            "mr",
            "un",
            "mg"
        ]
    },
    "11736": {
        "u": 11736,
        "nickname": "Sogen",
        "tags": [
            "bj",
            "bk",
            "un",
            "mg"
        ]
    },
    "11737": {
        "u": 11737,
        "nickname": "Sogen",
        "tags": [
            "mr",
            "un",
            "mg"
        ]
    },
    "11784": {
        "u": 11784,
        "nickname": "Sogen",
        "tags": [
            "mr",
            "su"
        ]
    },
    "11789": {
        "u": 11789,
        "nickname": "Sogen",
        "tags": [
            "mr",
            "mg",
            "su"
        ]
    },
    "11828": {
        "u": 11828,
        "nickname": "Sogen",
        "tags": [
            "mg"
        ]
    },
    "12490": {
        "u": 12490,
        "nickname": "Sogen",
        "world": "Beauty and the Beast",
        "sub": "None"
    },
    "13842": {
        "u": 13842,
        "nickname": "SunshineDreamer",
        "image": "ae7ac21a70d25f61547165192e50cc3e.jpg",
        "source": "https://chan.sankakucomplex.com/post/show/3767962"
    },
    "13924": {
        "u": 13924,
        "nickname": "Broken Genesis",
        "tags": [
            "C"
        ]
    },
    "13943": {
        "u": 13943,
        "nickname": "Akado",
        "tags": [
            "hr",
            "hz",
            "cl",
            "dr",
            "pl",
            "ih",
            "rl",
            "sa",
            "rg",
            "cm"
        ],
        "image": "ack_fateapocrypha_fate__28series_29_3779408.jpeg",
        "source": "http://img10.reactor.cc/pics/post/Anime-lancer-of-black-FateApocrypha-Fate-%28series%29-3779408.jpeg"
    },
    "1015276": {
        "u": 1015276,
        "nickname": "Anongus",
        "world": "Manyu Hikenchou"
    },
    "1041190": {
        "u": 1041190,
        "nickname": "else",
        "image": "KAjnSET.jpg",
        "source": "https://cdn.donmai.us/sample/92/55/__elesis_and_blazing_heart_elsword_drawn_by_alice360__sample-925543120df472d7f86ca4b02678a722.jpg"
    },
    "1066031": {
        "u": 1066031,
        "nickname": "Sogen",
        "tags": [
            "ur"
        ]
    },
    "1089016": {
        "u": 1089016,
        "nickname": "Sogen",
        "tags": [
            "cm"
        ]
    },
    "1122460": {
        "u": 1122460,
        "nickname": "@Led",
        "tags": [
            "th"
        ]
    },
    "1127226": {
        "u": 1127226,
        "nickname": "FavChanger",
        "tier": 3,
        "arg": "Quark, while intelligent, is not shown to be exceptional enough to be a leader in any field. He's a normal kid in an abnormal situation."
    },
    "1162745": {
        "u": 1162745,
        "nickname": "SunshineDreamer",
        "tags": [
            "U"
        ],
        "image": "ZFkdOWJ.jpg",
        "source": "https://comicvine.gamespot.com/a/uploads/original/0/3347/1255682-starlight_3.jpg"
    },
    "1282951": {
        "u": 1282951,
        "nickname": "lucho9",
        "tags": [
            "rl",
            "al",
            "cm"
        ],
        "image": "u46zcrliqa771.png",
        "source": "https://i.redd.it/u46zcrliqa771.png"
    },
    "1300978": {
        "u": 1300978,
        "nickname": "Cyrus",
        "tags": [
            "hr",
            "pi",
            "cm"
        ],
        "sub": "None"
    },
    "1376292": {
        "u": 1376292,
        "nickname": "beato",
        "world": "Umineko When They Cry",
        "sub": "None"
    },
    "1389959": {
        "u": 1389959,
        "nickname": "SunshineDreamer",
        "image": "caratn.png",
        "source": "https://cdn.discordapp.com/attachments/868800506364035074/995767982502465546/unknown.png"
    },
    "1421553": {
        "u": 1421553,
        "nickname": "SunshineDreamer",
        "image": "dranown.png",
        "source": "https://cdn.discordapp.com/attachments/868800506364035074/995769974880735333/unknown.png"
    },
    "1497950": {
        "u": 1497950,
        "nickname": "Cyrus",
        "tags": [
            "st",
            "Revolutionary",
            "rl",
            "cm",
            "sh"
        ],
        "sub": "None"
    },
    "1563916": {
        "u": 1563916,
        "nickname": "Paragon_4376",
        "tags": [
            "sr",
            "cm"
        ]
    },
    "1621887": {
        "u": 1621887,
        "nickname": "Cyrus",
        "tags": [
            "O",
            "hr",
            "hz",
            "cl",
            "sc"
        ],
        "sub": "None",
        "name": "S-Hawk"
    },
    "1645887": {
        "u": 1645887,
        "nickname": "Lunasmeow",
        "tags": [
            "MILF"
        ]
    },
    "1679798": {
        "u": 1679798,
        "nickname": "Sogen",
        "tags": [
            "hz"
        ]
    },
    "1691675": {
        "u": 1691675,
        "nickname": "SunshineDreamer",
        "image": "aldirown.png",
        "source": "https://cdn.discordapp.com/attachments/868800506364035074/995769386960957460/unknown.png"
    },
    "1768086": {
        "u": 1768086,
        "nickname": "SunshineDreamer",
        "image": "jFkDJls.jpg",
        "source": "https://i.pinimg.com/originals/1a/79/21/1a7921d94620e817cb8f22b96ba21b52.jpg"
    },
    "1769665": {
        "u": 1769665,
        "nickname": "SunshineDreamer",
        "name": "Aasdier (projection only)"
    },
    "1775796": {
        "u": 1775796,
        "nickname": "Sogen",
        "tags": [
            "hz",
            "id",
            "ur"
        ]
    },
    "1779882": {
        "u": 1779882,
        "nickname": "Sogen",
        "tags": [
            "hz",
            "id",
            "ur"
        ]
    },
    "1801147": {
        "u": 1801147,
        "nickname": "SunshineDreamer",
        "world": "Warcraft - Azeroth"
    },
    "1821335": {
        "u": 1821335,
        "nickname": "SunshineDreamer",
        "world": "Warcraft - Azeroth"
    },
    "1849697": {
        "u": 1849697,
        "nickname": "SunshineDreamer",
        "image": "windown.png",
        "source": "https://cdn.discordapp.com/attachments/868800506364035074/995765671218655322/unknown.png"
    },
    "1871390": {
        "u": 1871390,
        "nickname": "Cyrus",
        "tags": [
            "sc",
            "ev",
            "vn",
            "cm"
        ],
        "sub": "None"
    },
    "1909176": {
        "u": 1909176,
        "nickname": "Demontty",
        "tags": [
            "cr",
            "pr",
            "sh"
        ]
    },
    "1963047": {
        "u": 1963047,
        "nickname": "Sogen",
        "tags": [
            "hz",
            "id",
            "ur"
        ]
    },
    "2141437": {
        "u": 2141437,
        "nickname": "FavChanger",
        "tags": [
            "M",
            "ps",
            "ur",
            "ip",
            "sh",
            "O"
        ],
        "sub": "None",
        "world": "Persona 5"
    },
    "2160952": {
        "u": 2160952,
        "nickname": "Sogen",
        "tags": [
            "hr",
            "hz",
            "cl",
            "cm"
        ]
    },
    "2212833": {
        "u": 2212833,
        "nickname": "beato",
        "world": "Umineko When They Cry",
        "sub": "None",
        "tags": [
            "hz",
            "ps",
            "id",
            "sc",
            "rw"
        ]
    },
    "2353097": {
        "u": 2353097,
        "nickname": "SunshineDreamer",
        "world": "Ai No Puirzun/Prison School"
    },
    "2453952": {
        "u": 2453952,
        "nickname": "Rhivan",
        "tags": [
            "hz",
            "cl",
            "ps",
            "di",
            "th",
            "pt"
        ]
    },
    "2477353": {
        "u": 2477353,
        "nickname": "TheFlatCat",
        "tags": [
            "ev",
            "ps",
            "sc",
            "sh"
        ]
    },
    "2559092": {
        "u": 2559092,
        "nickname": "Cyrus",
        "tags": [
            "st",
            "cm",
            "gi"
        ]
    },
    "2574688": {
        "u": 2574688,
        "nickname": "SetDarsia",
        "tags": [
            "F",
            "ps",
            "M"
        ]
    },
    "2612463": {
        "u": 2612463,
        "nickname": "Broken Genesis",
        "tags": [
            "ye"
        ]
    },
    "2665750": {
        "u": 2665750,
        "nickname": "SunshineDreamer",
        "image": "arhturown.png",
        "source": "https://media.discordapp.net/attachments/868800506364035074/995746215830503554/unknown.png"
    },
    "2680502": {
        "u": 2680502,
        "nickname": "Cyrus",
        "tags": [
            "hr",
            "sl",
            "dm",
            "pi",
            "rl",
            "cm"
        ],
        "sub": "None"
    },
    "2719602": {
        "u": 2719602,
        "nickname": "TheFlatCat",
        "tags": [
            "cr",
            "di",
            "ev",
            "sh"
        ]
    },
    "2757216": {
        "u": 2757216,
        "nickname": "Sogen",
        "tags": [
            "hz",
            "id",
            "ur"
        ]
    },
    "2839912": {
        "u": 2839912,
        "nickname": "Eledao",
        "tags": [
            "st",
            "cl",
            "ml",
            "sl",
            "pr",
            "Bartender"
        ],
        "image": "__jill_stingray_va_11_hall_a_drawn_by_bl_ess__sample-0807f96985dd5b959a9928900cf0fe6d.jpg",
        "source": "https://cdn.donmai.us/sample/08/07/__jill_stingray_va_11_hall_a_drawn_by_bl_ess__sample-0807f96985dd5b959a9928900cf0fe6d.jpg",
        "nsfw": "https://pictures.hentai-foundry.com/s/Silveztra/863362/Silveztra-863362-Jill_stingray.png",
        "name": "Jill Stingray"
    },
    "2885966": {
        "u": 2885966,
        "nickname": "Sogen",
        "tags": [
            "st"
        ]
    },
    "2996116": {
        "u": 2996116,
        "nickname": "Cyrus",
        "tags": [
            "dh"
        ]
    },
    "3007196": {
        "u": 3007196,
        "nickname": "Sogen",
        "tags": [
            "ps"
        ]
    },
    "3015133": {
        "u": 3015133,
        "nickname": "Cyrus",
        "tags": [
            "sn",
            "cm"
        ]
    },
    "3106457": {
        "u": 3106457,
        "nickname": "Sogen",
        "tags": [
            "hz",
            "id",
            "ur"
        ]
    },
    "3158816": {
        "u": 3158816,
        "nickname": "LoLRaven",
        "tags": [
            "pr"
        ]
    },
    "3166039": {
        "u": 3166039,
        "nickname": "Cyrus",
        "tags": [
            "pi"
        ]
    },
    "3178803": {
        "u": 3178803,
        "nickname": "lucho9",
        "tags": [
            "ip",
            "al",
            "vn"
        ]
    },
    "3202831": {
        "u": 3202831,
        "nickname": "Cyrus",
        "tags": [
            "st",
            "sr",
            "rl",
            "sa"
        ],
        "sub": "None",
        "name": "Sengoku"
    },
    "3228719": {
        "u": 3228719,
        "nickname": "Nycaedemon",
        "image": "uyooown.png",
        "source": "https://cdn.discordapp.com/attachments/868800506364035074/995774887459303535/unknown.png"
    },
    "3276746": {
        "u": 3276746,
        "nickname": "Cyrus",
        "tags": [
            "st",
            "Mink",
            "sr",
            "cm"
        ],
        "sub": "None",
        "nsfw": "None"
    },
    "3293311": {
        "u": 3293311,
        "nickname": "Sogen",
        "tags": [
            "hz",
            "dr",
            "id",
            "ur"
        ]
    },
    "3320774": {
        "u": 3320774,
        "nickname": "noi",
        "nsfw": "https://lotus.paheal.net/_images/18b4c1fb898d2757d73f887f8301441f/3817759%20-%20Critical_Role%20Critical_Role%3A_The_Mighty_Nein%20Dungeons_and_Dragons%20Jester_Lavorre%20The_Traveler%20captain_popcorn%20tiefling.jpg"
    },
    "3334083": {
        "u": 3334083,
        "nickname": "Cyrus",
        "tags": [
            "hr",
            "Giant",
            "sl",
            "rl",
            "cm"
        ],
        "sub": "None"
    },
    "3415074": {
        "u": 3415074,
        "nickname": "Lunasmeow",
        "name": "Xue Wu (Donghua) / Mo Xue (Manhua)"
    },
    "3431065": {
        "u": 3431065,
        "nickname": "Sogen",
        "tags": [
            "cl",
            "sc",
            "cm"
        ]
    },
    "3446847": {
        "u": 3446847,
        "nickname": "Eledao",
        "tags": [
            "hr",
            "sd",
            "pr",
            "cm",
            "gi"
        ],
        "image": "https://i.imgur.com/FloJTyd.png",
        "source": "https://static.wikia.nocookie.net/suda51/images/b/ba/JulietsterlingRender.jpg/revision/latest/top-crop/width/360/height/450?cb=20110818165449",
        "nsfw": "http://pictures.hentai-foundry.com/m/MinaCream/480531/MinaCream-480531-Daily_Sketch_-_Juliet.jpg"
    },
    "3453551": {
        "u": 3453551,
        "nickname": "Cyrus",
        "tags": [
            "ml",
            "cm"
        ]
    },
    "3528400": {
        "u": 3528400,
        "nickname": "Digital_Devil",
        "tags": [
            "hz",
            "ps",
            "id",
            "sc",
            "di",
            "dn"
        ]
    },
    "3586211": {
        "u": 3586211,
        "nickname": "Sogen",
        "tags": [
            "ml",
            "cm"
        ]
    },
    "3586502": {
        "u": 3586502,
        "nickname": "SunshineDreamer",
        "image": "micawn.png",
        "source": "https://cdn.discordapp.com/attachments/868800506364035074/995767398890217592/unknown.png"
    },
    "3656815": {
        "u": 3656815,
        "nickname": "FavChanger",
        "tags": [
            "hp"
        ],
        "tier": 3,
        "arg": "Carlos is a SHIFTer, he can, without any knowledge of his abilities send information through time to his past self, and is later able to send his consciousness across timelines. This is at least a tier 4 power."
    },
    "3689163": {
        "u": 3689163,
        "nickname": "Hellboar",
        "tags": [
            "sd"
        ]
    },
    "3698412": {
        "u": 3698412,
        "nickname": "Cyrus",
        "tags": [
            "Giant",
            "sl",
            "pi",
            "sr",
            "ev",
            "vn",
            "cm"
        ],
        "sub": "None"
    },
    "3705605": {
        "u": 3705605,
        "nickname": "Anongus",
        "world": "Netoge no Yome"
    },
    "3731104": {
        "u": 3731104,
        "nickname": "Lunasmeow",
        "tags": [
            "rl"
        ]
    },
    "3741178": {
        "u": 3741178,
        "nickname": "SunshineDreamer",
        "world": "Warcraft - Azeroth"
    },
    "3751868": {
        "u": 3751868,
        "nickname": "SunshineDreamer",
        "world": "You're Under Arrest"
    },
    "3795443": {
        "u": 3795443,
        "nickname": "Cyrus",
        "tags": [
            "sc",
            "ev",
            "vn",
            "cm"
        ],
        "sub": "None"
    },
    "3805309": {
        "u": 3805309,
        "nickname": "Cyrus",
        "tags": [
            "st",
            "Mink",
            "sr",
            "rl",
            "cm"
        ],
        "sub": "None"
    },
    "3845107": {
        "u": 3845107,
        "nickname": "Sogen",
        "tags": [
            "hz",
            "id",
            "ur"
        ]
    },
    "3874186": {
        "u": 3874186,
        "nickname": "TDon123",
        "tags": [
            "tm",
            "tn"
        ]
    },
    "3889838": {
        "u": 3889838,
        "nickname": "Sogen",
        "tags": [
            "ml"
        ]
    },
    "3891209": {
        "u": 3891209,
        "nickname": "LoLRaven",
        "tags": [
            "sy"
        ]
    },
    "3956096": {
        "u": 3956096,
        "nickname": "SunshineDreamer",
        "image": "https://i.imgur.com/Gvo4FaYl.png",
        "source": "https://i.imgur.com/Gvo4FaY.png"
    },
    "3985986": {
        "u": 3985986,
        "nickname": "SunshineDreamer",
        "image": "grephwn.png",
        "source": "https://cdn.discordapp.com/attachments/868800506364035074/995768329346224128/unknown.png"
    },
    "3987753": {
        "u": 3987753,
        "nickname": "Cyrus",
        "tags": [
            "st",
            "Mink",
            "sr",
            "cm"
        ],
        "sub": "Mink Tribe"
    },
    "4041552": {
        "u": 4041552,
        "nickname": "Cyrus",
        "tags": [
            "hr",
            "Giant",
            "sl",
            "rl",
            "cm"
        ],
        "sub": "None"
    },
    "4049725": {
        "u": 4049725,
        "nickname": "SunshineDreamer",
        "image": "OIyypgq.jpg",
        "source": "https://pics.prcm.jp/reborn1123/40559755/jpeg/40559755_453x636.jpeg",
        "name": "Daniela/ Vongola Ottavo"
    },
    "4150582": {
        "u": 4150582,
        "nickname": "SunshineDreamer",
        "image": "c5556c88c97907c5d9a32a59a8a96872.jpg",
        "source": "https://i.pinimg.com/736x/c5/55/6c/c5556c88c97907c5d9a32a59a8a96872.jpg"
    },
    "4184551": {
        "u": 4184551,
        "nickname": "Zelred",
        "tags": [
            "su"
        ]
    },
    "4203175": {
        "u": 4203175,
        "nickname": "lucho9",
        "tags": [
            "ip",
            "lm",
            "al",
            "cm"
        ]
    },
    "4214844": {
        "u": 4214844,
        "nickname": "SunshineDreamer",
        "world": "Val x love"
    },
    "4257731": {
        "u": 4257731,
        "nickname": "Sogen",
        "tags": [
            "cs"
        ]
    },
    "4266409": {
        "u": 4266409,
        "nickname": "Eledao",
        "tags": [
            "O",
            "pr",
            "im",
            "M"
        ]
    },
    "4319144": {
        "u": 4319144,
        "nickname": "Sogen",
        "tags": [
            "hz",
            "id",
            "ur"
        ]
    },
    "4369916": {
        "u": 4369916,
        "nickname": "Ratcatcher",
        "nsfw": "https://lotus.paheal.net/_images/1ec80461eeb48445b01331ab5a15087d/2892816%20-%20Lila_Rossi%20Miraculous_Ladybug%20shisaireru.jpg"
    },
    "4583533": {
        "u": 4583533,
        "nickname": "Cyrus",
        "tags": [
            "sc",
            "ev",
            "gn",
            "rl",
            "vn",
            "cm"
        ],
        "sub": "None"
    },
    "4591369": {
        "u": 4591369,
        "nickname": "Sogen",
        "tags": [
            "st",
            "hz",
            "ps",
            "bj",
            "dr",
            "id",
            "pl",
            "ur",
            "cr",
            "sc",
            "ip"
        ]
    },
    "4602110": {
        "u": 4602110,
        "nickname": "SunshineDreamer",
        "sub": "None",
        "world": "Tolkien's Legendarium - Shadow of War"
    },
    "4643222": {
        "u": 4643222,
        "nickname": "SunshineDreamer",
        "world": "Ai No Purizun/Prison School"
    },
    "4653105": {
        "u": 4653105,
        "nickname": "TheFlatCat",
        "image": "Louanne_Katraine.png",
        "source": "https://upload.wikimedia.org/wikipedia/en/e/e4/Louanne_Katraine.png"
    },
    "4677072": {
        "u": 4677072,
        "nickname": "SunshineDreamer",
        "image": "lucaswn.png",
        "source": "https://media.discordapp.net/attachments/868800506364035074/995761010885529680/unknown.png"
    },
    "4772693": {
        "u": 4772693,
        "nickname": "Lunasmeow",
        "name": "Gu Qingbo"
    },
    "4776993": {
        "u": 4776993,
        "nickname": "Sogen",
        "tags": [
            "hz",
            "id",
            "ur"
        ]
    },
    "5061645": {
        "u": 5061645,
        "nickname": "Sogen",
        "tags": [
            "hz",
            "id",
            "ur"
        ]
    },
    "5067110": {
        "u": 5067110,
        "nickname": "Everythingman101",
        "tags": [
            "gi"
        ]
    },
    "5077258": {
        "u": 5077258,
        "nickname": "Eledao",
        "sub": "None"
    },
    "5078735": {
        "u": 5078735,
        "nickname": "Cyrus",
        "tags": [
            "O",
            "hr",
            "hz",
            "sc",
            "sl",
            "rl",
            "gi"
        ]
    },
    "5090923": {
        "u": 5090923,
        "nickname": "Sogen",
        "tags": [
            "hz",
            "id",
            "ur"
        ]
    },
    "5169774": {
        "u": 5169774,
        "nickname": "Paragon_4376",
        "tags": [
            "sl",
            "sa",
            "cm"
        ]
    },
    "5246244": {
        "u": 5246244,
        "nickname": "SunshineDreamer",
        "image": "kathlywn.png",
        "source": "https://media.discordapp.net/attachments/868800506364035074/995757348981321848/unknown.png"
    },
    "5394441": {
        "u": 5394441,
        "nickname": "Sogen",
        "tags": [
            "st",
            "hz",
            "cl",
            "ps",
            "dr",
            "id",
            "pl",
            "ur",
            "sc",
            "di",
            "ip",
            "dn",
            "dm"
        ]
    },
    "5463076": {
        "u": 5463076,
        "nickname": "Nycaedemon",
        "tags": [
            "st",
            "hz",
            "cr",
            "fm",
            "bk",
            "hp",
            "ai",
            "cm",
            "cu"
        ]
    },
    "5478030": {
        "u": 5478030,
        "nickname": "SunshineDreamer",
        "world": "Warcraft - Azeroth"
    },
    "5524626": {
        "u": 5524626,
        "nickname": "Cyrus",
        "sub": "None"
    },
    "5613529": {
        "u": 5613529,
        "nickname": "BuddhaFacepalmed",
        "tags": [
            "nn",
            "im"
        ]
    },
    "5620516": {
        "u": 5620516,
        "nickname": "Cyrus",
        "tags": [
            "st",
            "hr",
            "sl",
            "cm"
        ]
    },
    "5620861": {
        "u": 5620861,
        "nickname": "Cyrus",
        "tags": [
            "hr",
            "Giant",
            "cm",
            "sh"
        ],
        "sub": "None"
    },
    "5649754": {
        "u": 5649754,
        "nickname": "Cyrus",
        "tags": [
            "sc",
            "ev",
            "vn",
            "cm"
        ],
        "sub": "None"
    },
    "5676528": {
        "u": 5676528,
        "nickname": "Eledao",
        "tags": [
            "th",
            "cm"
        ],
        "image": "__deunan_knute_and_briareos_hecatonchires_appleseed_and_1_more_drawn_by_shirow_masamune__sample-56a0c64e801fb04bb3e7ccb84e961ce3.jpg",
        "source": "https://cdn.donmai.us/sample/56/a0/__deunan_knute_and_briareos_hecatonchires_appleseed_and_1_more_drawn_by_shirow_masamune__sample-56a0c64e801fb04bb3e7ccb84e961ce3.jpg",
        "name": "briareos hecatonchires"
    },
    "5685657": {
        "u": 5685657,
        "nickname": "SunshineDreamer",
        "image": "tessiawn.png",
        "source": "https://cdn.discordapp.com/attachments/868800506364035074/995750612719378563/unknown.png"
    },
    "5698252": {
        "u": 5698252,
        "nickname": "SunshineDreamer",
        "tier": 10,
        "arg": "Literally becomes reality. Should be TX, discussed on official WC discord"
    },
    "5778653": {
        "u": 5778653,
        "nickname": "Sogen",
        "tags": [
            "hz",
            "id",
            "ur"
        ]
    },
    "5782347": {
        "u": 5782347,
        "nickname": "Sogen",
        "tags": [
            "ps"
        ]
    },
    "5843643": {
        "u": 5843643,
        "nickname": "Sogen",
        "tags": [
            "di",
            "fm"
        ]
    },
    "5846906": {
        "u": 5846906,
        "nickname": "SunshineDreamer",
        "image": "3527d763b834741130f85c9778c569e6.png",
        "source": "https://i.pinimg.com/originals/35/27/d7/3527d763b834741130f85c9778c569e6.png"
    },
    "5853775": {
        "u": 5853775,
        "nickname": "Cyrus",
        "tags": [
            "hr",
            "hz"
        ],
        "sub": "None"
    },
    "5871906": {
        "u": 5871906,
        "nickname": "LoLRaven",
        "tags": [
            "ps",
            "sc",
            "ip",
            "sr",
            "cm",
            "sh"
        ]
    },
    "5890964": {
        "u": 5890964,
        "nickname": "Cyrus",
        "tags": [
            "st",
            "hr",
            "hz",
            "rl",
            "cm"
        ]
    },
    "5891542": {
        "u": 5891542,
        "nickname": "Cyrus",
        "tags": [
            "cm",
            "is"
        ]
    },
    "5987727": {
        "u": 5987727,
        "nickname": "Cyrus",
        "tags": [
            "st",
            "cl",
            "sc",
            "pi",
            "cm"
        ]
    },
    "6003927": {
        "u": 6003927,
        "nickname": "LoLRaven",
        "tags": [
            "ml",
            "dr",
            "sl",
            "su"
        ]
    },
    "6142561": {
        "u": 6142561,
        "nickname": "Lunasmeow",
        "tags": [
            "im"
        ]
    },
    "6201401": {
        "u": 6201401,
        "nickname": "SunshineDreamer",
        "world": "BattleTech"
    },
    "6203426": {
        "u": 6203426,
        "nickname": "Sogen",
        "tags": [
            "hz",
            "ps",
            "bj",
            "id",
            "pl",
            "ur",
            "ip",
            "im"
        ]
    },
    "6252345": {
        "u": 6252345,
        "nickname": "Uubrik",
        "tags": [
            "sa"
        ]
    },
    "6281652": {
        "u": 6281652,
        "nickname": "Cyrus",
        "tags": [
            "sl",
            "an",
            "dh",
            "en",
            "vn",
            "cm",
            "ci"
        ]
    },
    "6330419": {
        "u": 6330419,
        "nickname": "SunshineDreamer",
        "world": "Warcraft - Azeroth"
    },
    "6366140": {
        "u": 6366140,
        "nickname": "TheFlatCat",
        "tags": [
            "mt",
            "mo",
            "cm",
            "im",
            "sh"
        ]
    },
    "6416695": {
        "u": 6416695,
        "nickname": "Heaven Canceler",
        "tags": [
            "M",
            "O"
        ]
    },
    "6437813": {
        "u": 6437813,
        "nickname": "Nycaedemon",
        "tags": [
            "cl",
            "sc",
            "dn",
            "sa",
            "cm"
        ]
    },
    "6487518": {
        "u": 6487518,
        "nickname": "Soul Hunter ",
        "nsfw": "None"
    },
    "6543486": {
        "u": 6543486,
        "nickname": "Sogen",
        "world": "Frozen",
        "sub": "None"
    },
    "6561834": {
        "u": 6561834,
        "nickname": "Nycaedemon",
        "tags": [
            "hz",
            "cr",
            "vn",
            "rw"
        ]
    },
    "6575371": {
        "u": 6575371,
        "nickname": "TheFlatCat",
        "tags": [
            "hz",
            "sc"
        ]
    },
    "6581962": {
        "u": 6581962,
        "nickname": "Cyrus",
        "tags": [
            "st",
            "Mink",
            "sr",
            "cm"
        ],
        "sub": "None"
    },
    "6594546": {
        "u": 6594546,
        "nickname": "Nycaedemon",
        "tags": [
            "cm"
        ],
        "image": "gilyown.png",
        "source": "https://media.discordapp.net/attachments/868800506364035074/996863835887640637/unknown.png"
    },
    "6618310": {
        "u": 6618310,
        "nickname": "TRm",
        "tags": [
            "cb"
        ]
    },
    "6683885": {
        "u": 6683885,
        "nickname": "Cyrus",
        "tags": [
            "ml",
            "di",
            "dn",
            "rl"
        ],
        "sub": "None",
        "name": "Issho (Fujitora)"
    },
    "6690278": {
        "u": 6690278,
        "nickname": "SunshineDreamer",
        "tags": [
            "U"
        ],
        "world": "BattleTech"
    },
    "6784510": {
        "u": 6784510,
        "nickname": "noi",
        "tier": 3,
        "arg": "donno man, she can fly, ler lemur breathes fire and they attack with enough magical blasts to blow up large armored vehicles. that should be at least T4, maybe even T5. "
    },
    "6795472": {
        "u": 6795472,
        "nickname": "Cyrus",
        "tags": [
            "hr",
            "Giant",
            "sl",
            "pi",
            "cm"
        ],
        "sub": "None"
    },
    "6872149": {
        "u": 6872149,
        "nickname": "Cyrus",
        "sub": "None"
    },
    "6943997": {
        "u": 6943997,
        "nickname": "SunshineDreamer",
        "name": "Unnamed* Kingslayer"
    },
    "6945427": {
        "u": 6945427,
        "nickname": "Soul Hunter ",
        "tags": [
            "ps",
            "sc",
            "py",
            "dn"
        ]
    },
    "6949579": {
        "u": 6949579,
        "nickname": "TheFlatCat",
        "tags": [
            "hz",
            "sc"
        ]
    },
    "6957929": {
        "u": 6957929,
        "nickname": "SunshineDreamer",
        "tier": 3,
        "arg": "My mistake should be tier 2 instead"
    },
    "6962038": {
        "u": 6962038,
        "nickname": "SunshineDreamer",
        "world": "Dc"
    },
    "6965473": {
        "u": 6965473,
        "nickname": "Demontty",
        "tags": [
            "cl",
            "cr",
            "sl"
        ]
    },
    "6991293": {
        "u": 6991293,
        "nickname": "Sogen",
        "tags": [
            "st",
            "hr",
            "cl",
            "ml",
            "sc",
            "sl",
            "dc",
            "en",
            "gn",
            "cc",
            "cm",
            "ha"
        ]
    },
    "7082132": {
        "u": 7082132,
        "nickname": "Cyrus",
        "tags": [
            "gn",
            "cc",
            "cl",
            "sc",
            "en",
            "cb",
            "ev",
            "vn",
            "gi"
        ]
    },
    "7163378": {
        "u": 7163378,
        "nickname": "LoLRaven",
        "tags": [
            "rl"
        ]
    },
    "7175253": {
        "u": 7175253,
        "nickname": "@Led",
        "tags": [
            "th"
        ]
    },
    "7175776": {
        "u": 7175776,
        "nickname": "Everythingman101",
        "tags": [
            "ps",
            "de",
            "gn",
            "sa",
            "rg",
            "cm"
        ]
    },
    "7180939": {
        "u": 7180939,
        "nickname": "Sogen",
        "tags": [
            "un"
        ]
    },
    "7201043": {
        "u": 7201043,
        "nickname": "Eledao",
        "tags": [
            "O",
            "st",
            "hz",
            "cl",
            "ps",
            "dr",
            "pl",
            "cr",
            "pr",
            "im",
            "cs",
            "M"
        ]
    },
    "7243779": {
        "u": 7243779,
        "nickname": "Anongus",
        "tags": [
            "F"
        ]
    },
    "7268089": {
        "u": 7268089,
        "nickname": "Sogen",
        "tags": [
            "st",
            "ps",
            "dr",
            "cr",
            "di",
            "ip",
            "me",
            "su"
        ]
    },
    "7268594": {
        "u": 7268594,
        "nickname": "Lunasmeow",
        "tags": [
            "Tomboy"
        ]
    },
    "7273881": {
        "u": 7273881,
        "nickname": "beato",
        "tags": [
            "hp"
        ],
        "sub": "None"
    },
    "7300789": {
        "u": 7300789,
        "nickname": "Sogen",
        "tags": [
            "ml"
        ]
    },
    "7360723": {
        "u": 7360723,
        "nickname": "Eledao",
        "tags": [
            "hr",
            "sa",
            "cm",
            "Pilot"
        ],
        "image": "__intron_depot_drawn_by_shirow_masamune__sample-15df5a0c7369d1586f566c9f1e3c890b.jpg",
        "source": "https://cdn.donmai.us/sample/15/df/__intron_depot_drawn_by_shirow_masamune__sample-15df5a0c7369d1586f566c9f1e3c890b.jpg",
        "nsfw": "https://cdn.donmai.us/sample/ea/28/__deunan_knute_appleseed_drawn_by_shirow_masamune__sample-ea28d27b119098d71bc3c6cc5fe50780.jpg"
    },
    "7474986": {
        "u": 7474986,
        "nickname": "Chibikingsai",
        "image": "ro4t8millde41.jpg",
        "source": "https://i.redd.it/ro4t8millde41.jpg"
    },
    "7476998": {
        "u": 7476998,
        "nickname": "Sogen",
        "tags": [
            "st",
            "hz",
            "ps",
            "bj",
            "dr",
            "id",
            "pl",
            "ur",
            "cr",
            "sc",
            "di",
            "ip",
            "bk",
            "dn"
        ]
    },
    "7495929": {
        "u": 7495929,
        "nickname": "SunshineDreamer",
        "sub": "Earth-616"
    },
    "7567452": {
        "u": 7567452,
        "nickname": "Cyrus",
        "tags": [
            "sn",
            "Mink",
            "cl",
            "sc",
            "sl",
            "sr",
            "cm"
        ],
        "sub": "None"
    },
    "7703754": {
        "u": 7703754,
        "nickname": "Sogen",
        "tags": [
            "pr",
            "cs"
        ]
    },
    "7784784": {
        "u": 7784784,
        "nickname": "Sogen",
        "tags": [
            "st",
            "hr",
            "cl",
            "ps",
            "bj",
            "sc",
            "ip",
            "bk",
            "cm"
        ]
    },
    "7913254": {
        "u": 7913254,
        "nickname": "SunshineDreamer",
        "image": "https://i.imgur.com/ZYKtTsLl.png",
        "source": "https://i.imgur.com/ZYKtTsL.png"
    },
    "8000241": {
        "u": 8000241,
        "nickname": "raiden",
        "tags": [
            "st",
            "hz",
            "cl",
            "id",
            "sc",
            "gn"
        ]
    },
    "8006696": {
        "u": 8006696,
        "nickname": "Sogen",
        "world": "Frozen",
        "sub": "None"
    },
    "8186264": {
        "u": 8186264,
        "nickname": "Sogen",
        "tags": [
            "hz",
            "id",
            "ur"
        ]
    },
    "8202974": {
        "u": 8202974,
        "nickname": "Cyrus",
        "tags": [
            "sl",
            "pi",
            "cm"
        ]
    },
    "8204731": {
        "u": 8204731,
        "nickname": "Sogen",
        "tags": [
            "ps"
        ]
    },
    "8228616": {
        "u": 8228616,
        "nickname": "Cyrus",
        "tags": [
            "di",
            "sc",
            "cf",
            "tp",
            "cm",
            "gi"
        ],
        "sub": "None"
    },
    "8309569": {
        "u": 8309569,
        "nickname": "SunshineDreamer",
        "world": "i grow stronger by eating"
    },
    "8322951": {
        "u": 8322951,
        "nickname": "Cyrus",
        "tags": [
            "cl",
            "sc",
            "di",
            "sl",
            "ar",
            "sa",
            "cm",
            "gi"
        ]
    },
    "8410975": {
        "u": 8410975,
        "nickname": "Eledao",
        "tags": [
            "cl",
            "th",
            "gi"
        ]
    },
    "8426240": {
        "u": 8426240,
        "nickname": "LoLRaven",
        "tags": [
            "dh",
            "de"
        ]
    },
    "8454569": {
        "u": 8454569,
        "nickname": "Hellboar",
        "tags": [
            "sd"
        ]
    },
    "8564755": {
        "u": 8564755,
        "nickname": "SunshineDreamer",
        "image": "https://i.imgur.com/JIAj9ANl.png",
        "source": "https://i.imgur.com/JIAj9AN.png"
    },
    "8660660": {
        "u": 8660660,
        "nickname": "Nycaedemon",
        "tags": [
            "sr"
        ],
        "image": "shinown.png",
        "source": "https://cdn.discordapp.com/attachments/868800506364035074/995772272725983372/unknown.png"
    },
    "8686342": {
        "u": 8686342,
        "nickname": "Riggnarock",
        "nsfw": "None"
    },
    "8703783": {
        "u": 8703783,
        "nickname": "TheFlatCat",
        "tags": [
            "hz",
            "sc"
        ]
    },
    "8753625": {
        "u": 8753625,
        "nickname": "Sogen",
        "world": "Frozen",
        "sub": "None"
    },
    "8773279": {
        "u": 8773279,
        "nickname": "SunshineDreamer",
        "world": "Warcraft - Azeroth"
    },
    "8795974": {
        "u": 8795974,
        "nickname": "SunshineDreamer",
        "world": "Ai No Purizun/Prison School"
    },
    "8858822": {
        "u": 8858822,
        "nickname": "SunshineDreamer",
        "world": "Val X Love"
    },
    "8872886": {
        "u": 8872886,
        "nickname": "Nycaedemon",
        "tags": [
            "st",
            "sa",
            "sh"
        ],
        "image": "unleen.png",
        "source": "https://cdn.discordapp.com/attachments/868800506364035074/995776082827558982/unknown.png"
    },
    "8886681": {
        "u": 8886681,
        "nickname": "Cyrus",
        "tags": [
            "st",
            "Mink",
            "sr",
            "rl",
            "cm"
        ],
        "sub": "None"
    },
    "9003053": {
        "u": 9003053,
        "nickname": "Sogen",
        "tags": [
            "st",
            "ps",
            "bj",
            "dr",
            "pl",
            "ur",
            "cr",
            "sc",
            "di",
            "dn"
        ]
    },
    "9014716": {
        "u": 9014716,
        "nickname": "SunshineDreamer",
        "world": "Warcraft - Azeroth"
    },
    "9074917": {
        "u": 9074917,
        "nickname": "SunshineDreamer",
        "world": "Warcraft - Azeroth"
    },
    "9133627": {
        "u": 9133627,
        "nickname": "@Led",
        "image": "VydAhbw.jpg",
        "source": "https://pbs.twimg.com/media/FYM2MQOagAAyPoi.jpg"
    },
    "9257306": {
        "u": 9257306,
        "nickname": "SunshineDreamer",
        "sub": "None",
        "world": "Marvel (616)"
    },
    "9276646": {
        "u": 9276646,
        "nickname": "Cyrus",
        "tags": [
            "st",
            "rl"
        ],
        "sub": "None"
    },
    "9280224": {
        "u": 9280224,
        "nickname": "Cyrus",
        "tags": [
            "pi"
        ],
        "sub": "Mink Tribe"
    },
    "9288619": {
        "u": 9288619,
        "nickname": "TheFlatCat",
        "tags": [
            "cl",
            "ps",
            "cr"
        ]
    },
    "9314247": {
        "u": 9314247,
        "nickname": "Cyrus",
        "tags": [
            "st",
            "ml",
            "sc",
            "di",
            "tc",
            "rl",
            "cm"
        ]
    },
    "9367369": {
        "u": 9367369,
        "nickname": "Cyrus",
        "tags": [
            "st",
            "sl",
            "an",
            "dh",
            "rl",
            "cm",
            "te"
        ]
    },
    "9459191": {
        "u": 9459191,
        "nickname": "FavChanger",
        "tags": [
            "st"
        ]
    },
    "9479160": {
        "u": 9479160,
        "nickname": "Cyrus",
        "tier": 5,
        "arg": "Sorry, made a mistake. She's stated in the Wiki to be a Powerhouse on par with other Top Commanders."
    },
    "9504412": {
        "u": 9504412,
        "nickname": "Cyrus",
        "tags": [
            "st",
            "sr",
            "cm"
        ]
    },
    "9548057": {
        "u": 9548057,
        "nickname": "Sogen",
        "tags": [
            "hz",
            "id",
            "ur"
        ]
    },
    "9618865": {
        "u": 9618865,
        "nickname": "anosh",
        "tags": [
            "hz",
            "cl",
            "ps",
            "dr",
            "pl",
            "sc",
            "di"
        ]
    },
    "9624502": {
        "u": 9624502,
        "nickname": "Sogen",
        "tags": [
            "hr",
            "hz",
            "cl"
        ]
    },
    "9648390": {
        "u": 9648390,
        "nickname": "SunshineDreamer",
        "world": "Battle Angel Alita"
    },
    "9678014": {
        "u": 9678014,
        "nickname": "Cyrus",
        "tags": [
            "st",
            "Mink",
            "sr",
            "cm"
        ],
        "sub": "None"
    },
    "9729036": {
        "u": 9729036,
        "nickname": "Chibikingsai",
        "tags": [
            "P",
            "cb"
        ]
    },
    "9740156": {
        "u": 9740156,
        "nickname": "Dreadrotz",
        "tags": [
            "dh"
        ]
    },
    "9740876": {
        "u": 9740876,
        "nickname": "Sogen",
        "tags": [
            "ur",
            "su"
        ]
    },
    "9775846": {
        "u": 9775846,
        "nickname": "Sogen",
        "tags": [
            "un"
        ]
    },
    "9784300": {
        "u": 9784300,
        "nickname": "LoLRaven",
        "tags": [
            "ml",
            "id",
            "rg"
        ]
    },
    "9786900": {
        "u": 9786900,
        "nickname": "TheFlatCat",
        "tags": [
            "cm",
            "sh",
            "Pilot",
            "Mechanic"
        ]
    },
    "9827048": {
        "u": 9827048,
        "nickname": "SunshineDreamer",
        "image": "https://i.imgur.com/QyYxhw4l.png",
        "source": "https://i.imgur.com/QyYxhw4.png"
    },
    "9852177": {
        "u": 9852177,
        "nickname": "Sogen",
        "tags": [
            "hz",
            "dr",
            "id",
            "ur",
            "cr",
            "di",
            "dn"
        ]
    },
    "9856971": {
        "u": 9856971,
        "nickname": "Shine",
        "tags": [
            "pr",
            "os"
        ],
        "image": "ttCqtKQ.jpg",
        "source": "https://cdn.donmai.us/original/b8/25/__ochiai_kinjo_no_hito_no_nakimushi_drawn_by_zyugoya__b8257eac5c6bcc6d3ee58579efe224a4.jpg",
        "nsfw": "None"
    },
    "9915276": {
        "u": 9915276,
        "nickname": "Sogen",
        "tags": [
            "hz",
            "id",
            "ur",
            "sc",
            "di",
            "dn"
        ]
    },
    "9930605": {
        "u": 9930605,
        "nickname": "Sogen",
        "tags": [
            "ps",
            "ur",
            "cr",
            "sc"
        ]
    },
    "9933765": {
        "u": 9933765,
        "nickname": "Sogen",
        "world": "Frozen",
        "sub": "None"
    },
    "9935075": {
        "u": 9935075,
        "nickname": "SunshineDreamer",
        "image": "9116276bf82bc16ca945ad5879b1ef1519f320b5r1-300-300v2_00.jpg",
        "source": "http://pm1.narvii.com/7098/9116276bf82bc16ca945ad5879b1ef1519f320b5r1-300-300v2_00.jpg"
    },
    "9970045": {
        "u": 9970045,
        "nickname": "kong",
        "world": "Journey to The West",
        "name": "Sun wukong"
    }
}